raynbow/__init__.py
raynbow/colorspaces.py
raynbow/data.py
raynbow/io.py
raynbow/plotting.py
raynbow/utilities.py
raynbow-0.1.5.dist-info/METADATA
raynbow-0.1.5.dist-info/RECORD
raynbow-0.1.5.dist-info/WHEEL
raynbow-0.1.5.dist-info/top_level.txt
