Metadata-Version: 2.1
Name: raynbow
Version: 0.1.5
Summary: A python module for analysis of spectral data
Home-page: https://github.com/brandondube/raynbow
Author: Brandon Dube
Author-email: brandondube@gmail.com
License: MIT
Platform: UNKNOWN
Classifier: Development Status :: 4 - Beta
Classifier: Intended Audience :: Science/Research
Classifier: License :: OSI Approved :: MIT License
Classifier: Programming Language :: Python :: 3.6
Requires-Dist: numpy
Requires-Dist: scipy
Requires-Dist: matplotlib
